.gitignore
CHANGES.rst
MANIFEST.in
README.rst
setup.cfg
setup.py
docs/.gitignore
docs/Makefile
docs/api.rst
docs/conf.py
docs/glossary.rst
docs/index.rst
docs/_build/html/searchindex.js
docs/_build/html/_sources/api.txt
docs/_build/html/_sources/glossary.txt
docs/_build/html/_sources/index.txt
docs/_build/html/_sources/_themes/README.txt
docs/_build/html/_static/basic.css
docs/_build/html/_static/dialog-note.png
docs/_build/html/_static/dialog-seealso.png
docs/_build/html/_static/dialog-topic.png
docs/_build/html/_static/dialog-warning.png
docs/_build/html/_static/doctools.js
docs/_build/html/_static/epub.css
docs/_build/html/_static/file.png
docs/_build/html/_static/footerbg.png
docs/_build/html/_static/headerbg.png
docs/_build/html/_static/ie6.css
docs/_build/html/_static/jquery.js
docs/_build/html/_static/middlebg.png
docs/_build/html/_static/minus.png
docs/_build/html/_static/plus.png
docs/_build/html/_static/pygments.css
docs/_build/html/_static/pylons-latex.png
docs/_build/html/_static/pylons-small.png
docs/_build/html/_static/pylons.css
docs/_build/html/_static/pylons.ico
docs/_build/html/_static/pylons.png
docs/_build/html/_static/pyramid-latex.png
docs/_build/html/_static/pyramid-small.png
docs/_build/html/_static/pyramid.ico
docs/_build/html/_static/pyramid.png
docs/_build/html/_static/searchtools.js
docs/_build/html/_static/transparent.gif
docs/_build/html/_static/underscore.js
docs/_themes/.gitignore
docs/_themes/CONTRIBUTORS.txt
docs/_themes/LICENSE.txt
docs/_themes/README.rst
docs/_themes/pylons/static/dialog-note.png
docs/_themes/pylons/static/dialog-seealso.png
docs/_themes/pylons/static/dialog-topic.png
docs/_themes/pylons/static/dialog-warning.png
docs/_themes/pylons/static/epub.css
docs/_themes/pylons/static/footerbg.png
docs/_themes/pylons/static/headerbg.png
docs/_themes/pylons/static/ie6.css
docs/_themes/pylons/static/middlebg.png
docs/_themes/pylons/static/pylons-latex.png
docs/_themes/pylons/static/pylons-small.png
khufu_sqlalchemy.egg-info/PKG-INFO
khufu_sqlalchemy.egg-info/SOURCES.txt
khufu_sqlalchemy.egg-info/dependency_links.txt
khufu_sqlalchemy.egg-info/entry_points.txt
khufu_sqlalchemy.egg-info/not-zip-safe
khufu_sqlalchemy.egg-info/requires.txt
khufu_sqlalchemy.egg-info/top_level.txt
