Metadata-Version: 1.0
Name: khufu-sqlalchemy
Version: 1.0a1
Summary: SQLAlchemy bindings for Pyramid
Home-page: http://khufuproject.github.com/khufu_sqlalchemy/
Author: Rocky Burt
Author-email: rocky@serverzen.com
License: BSD
Keywords: pyramid sqlalchemy khufu transaction
Platform: UNKNOWN
Classifier: License :: OSI Approved :: BSD License
Classifier: Programming Language :: Python
Classifier: Topic :: Internet :: WWW/HTTP :: WSGI
